AUTHORS
ChangeLog
Dockerfile
LICENSE
README.md
README.zh.md
format_code.sh
harborrc_demo
requirements.txt
set_bash_completion.sh
setup.cfg
setup.py
test-requirements.txt
tox.ini
harborclient/__init__.py
harborclient/api_versions.py
harborclient/base.py
harborclient/client.py
harborclient/exceptions.py
harborclient/shell.py
harborclient/utils.py
harborclient/v2/__init__.py
harborclient/v2/client.py
harborclient/v2/configurations.py
harborclient/v2/jobs.py
harborclient/v2/logs.py
harborclient/v2/projects.py
harborclient/v2/repositories.py
harborclient/v2/searcher.py
harborclient/v2/shell.py
harborclient/v2/statistics.py
harborclient/v2/systeminfo.py
harborclient/v2/targets.py
harborclient/v2/users.py
python_harborclient.egg-info/PKG-INFO
python_harborclient.egg-info/SOURCES.txt
python_harborclient.egg-info/dependency_links.txt
python_harborclient.egg-info/entry_points.txt
python_harborclient.egg-info/not-zip-safe
python_harborclient.egg-info/pbr.json
python_harborclient.egg-info/requires.txt
python_harborclient.egg-info/top_level.txt
tools/pretty_tox.sh